glver/__init__.py
glver/__main__.py
glver/glver.cp35-win32.pyd
glver-1.0.0.dist-info/DESCRIPTION.rst
glver-1.0.0.dist-info/METADATA
glver-1.0.0.dist-info/RECORD
glver-1.0.0.dist-info/WHEEL
glver-1.0.0.dist-info/metadata.json
glver-1.0.0.dist-info/top_level.txt
