Metadata-Version: 1.0
Name: glver
Version: 1.0.0
Summary: Python: Determine OpenGL version.
Home-page: https://github.com/cprogrammer1994/glver
Author: Szabolcs Dombi
Author-email: cprogrammer1994@gmail.com
License: UNKNOWN
Platform: UNKNOWN
